README.rst
setup.py
replicable/__init__.py
replicable/__version__.py
replicable/spec.py
replicable.egg-info/PKG-INFO
replicable.egg-info/SOURCES.txt
replicable.egg-info/dependency_links.txt
replicable.egg-info/requires.txt
replicable.egg-info/top_level.txt
replicable/tests/__init__.py
replicable/tests/test_assemble.py
replicable/tests/test_delayed.py
replicable/tests/test_execute.py
replicable/tests/test_filter.py
replicable/tests/test_index.py
replicable/tests/test_map.py
replicable/tests/test_persistence.py
replicable/tests/test_reduce.py
replicable/tests/test_resilience.py
replicable/tests/test_specification.py
replicable/tests/test_versioning.py